bassutils/__init__.py
bassutils/abc.py
bassutils/text.py
bassutils-0.0.2.dist-info/LICENSE
bassutils-0.0.2.dist-info/METADATA
bassutils-0.0.2.dist-info/WHEEL
bassutils-0.0.2.dist-info/top_level.txt
bassutils-0.0.2.dist-info/RECORD
